README.txt
setup.py
lmfhawq/__init__.py
lmfhawq.egg-info/PKG-INFO
lmfhawq.egg-info/SOURCES.txt
lmfhawq.egg-info/dependency_links.txt
lmfhawq.egg-info/requires.txt
lmfhawq.egg-info/top_level.txt
lmfhawq/dag/__init__.py
lmfhawq/dag/data_gcjs.py
lmfhawq/dag/data_ggzy.py
lmfhawq/dag/data_qycg.py
lmfhawq/dag/data_zfcg.py
lmfhawq/dag/gcjs.py
lmfhawq/dag/ggzy.py
lmfhawq/dag/qycg.py
lmfhawq/dag/zfcg.py
lmfhawq/dag/template/gcjs.txt
lmfhawq/dag/template/ggzy.txt
lmfhawq/dag/template/qycg.txt
lmfhawq/dag/template/zfcg.txt
lmfhawq/etl/__init__.py
lmfhawq/etl/dayn.py
lmfhawq/etl/hawqbyquyu.py
lmfhawq/etl/hawqbytime.py
lmfhawq/etl/topg.py
lmfhawq/etl/app/__init__.py
lmfhawq/etl/app/db.py
lmfhawq/etl/app/dongfeng.py
lmfhawq/etl/app/hawqupdate.py
lmfhawq/etl/app/key.txt
lmfhawq/etl/app/kunming.py
lmfhawq/hdb/__init__.py
lmfhawq/hdb/app.py
lmfhawq/hdb/data.py
lmfhawq/hdb/ext_zhongbiaoren.py
lmfhawq/hdb/remote.py
lmfhawq/hdb/zhongbiaoren2app.py
lmfhawq/hdb/zl.py
lmfhawq/hdb/zl_hq2ap.py
lmfhawq/hdb/zldb.py
lmfhawq/hdb/zlt_hxr.py
lmfhawq/hdb/zlt_zhongbiaoren.py